reverser/Reverser.py
reverser/__init__.py
reverser-2.0.0.dist-info/METADATA
reverser-2.0.0.dist-info/WHEEL
reverser-2.0.0.dist-info/licenses/LICENSE
reverser-2.0.0.dist-info/RECORD
