Metadata-Version: 2.1
Name: reverser
Version: 2.0.0
Summary: A small reverser package to reverse a list, tuple, string, int, or dict
Project-URL: Homepage, https://github.com/pypa/sampleproject
Project-URL: My GitHub, https://github.com/beastboixdna
Project-URL: Bug Tracker, https://github.com/pypa/sampleproject/issues
Author-email: Beast Boi <beastboigithub89@gmail.com>
License-File: LICENSE
Classifier: License :: OSI Approved :: MIT License
Classifier: Operating System :: OS Independent
Classifier: Programming Language :: Python :: 3
Requires-Python: >=3.7
